_view.cpython-39-aarch64-linux-gnu.so
view.py-1.0.0a10.dist-info/WHEEL
view.py-1.0.0a10.dist-info/LICENSE
view.py-1.0.0a10.dist-info/top_level.txt
view.py-1.0.0a10.dist-info/entry_points.txt
view.py-1.0.0a10.dist-info/RECORD
view.py-1.0.0a10.dist-info/METADATA
view/__main__.py
view/_codec.py
view/typecodes.py
view/__init__.py
view/config.py
view/_loader.py
view/py.typed
view/response.py
view/templates.py
view/build.py
view/_docs.py
view/components.py
view/patterns.py
view/logging.py
view/util.py
view/app.py
view/typing.py
view/_util.py
view/routing.py
view/_parsers.py
view/__about__.py
view/exceptions.py
view/_logging.py
view/databases.py
