Metadata-Version: 2.1
Name: view.py
Version: 1.0.0a10
Summary: The Batteries-Detachable Web Framework.
Author-email: ZeroIntensity <zintensitydev@gmail.com>
License: MIT
Project-URL: Documentation, https://view.zintensity.dev
Project-URL: Issues, https://github.com/ZeroIntensity/view.py/issues
Project-URL: Source, https://github.com/ZeroIntensity/view.py
Project-URL: Funding, https://github.com/sponsors/ZeroIntensity
Classifier: Programming Language :: Python
Classifier: Programming Language :: Python :: 3.7
Classifier: Programming Language :: Python :: 3.8
Classifier: Programming Language :: Python :: 3.9
Classifier: Programming Language :: Python :: 3.10
Classifier: Programming Language :: Python :: 3.11
Classifier: Programming Language :: Python :: Implementation :: CPython
Requires-Python: >=3.8
License-File: LICENSE
Requires-Dist: rich
Requires-Dist: click
Requires-Dist: typing-extensions
Requires-Dist: ujson
Requires-Dist: configzen
Requires-Dist: aiofiles
Requires-Dist: prompts.py
Provides-Extra: databases
Requires-Dist: psycopg2-binary ; extra == 'databases'
Requires-Dist: mysql-connector-python ; extra == 'databases'
Requires-Dist: pymongo ; extra == 'databases'
Requires-Dist: aiosqlite ; extra == 'databases'
Provides-Extra: dev
Requires-Dist: ruff ; extra == 'dev'
Requires-Dist: mypy ; extra == 'dev'
Provides-Extra: fancy
Requires-Dist: psutil ; extra == 'fancy'
Requires-Dist: plotext ; extra == 'fancy'
Provides-Extra: full
Requires-Dist: psutil ; extra == 'full'
Requires-Dist: plotext ; extra == 'full'
Requires-Dist: beautifulsoup4 ; extra == 'full'
Requires-Dist: jinja2 ; extra == 'full'
Requires-Dist: mako ; extra == 'full'
Requires-Dist: django ; extra == 'full'
Requires-Dist: chameleon ; extra == 'full'
Requires-Dist: attrs ; extra == 'full'
Requires-Dist: psycopg2-binary ; extra == 'full'
Requires-Dist: mysql-connector-python ; extra == 'full'
Requires-Dist: pymongo ; extra == 'full'
Requires-Dist: aiosqlite ; extra == 'full'
Requires-Dist: markdown ; extra == 'full'
Requires-Dist: uvicorn ; extra == 'full'
Requires-Dist: hypercorn ; extra == 'full'
Requires-Dist: daphne ; extra == 'full'
Provides-Extra: servers
Requires-Dist: uvicorn ; extra == 'servers'
Requires-Dist: hypercorn ; extra == 'servers'
Requires-Dist: daphne ; extra == 'servers'
Provides-Extra: templates
Requires-Dist: beautifulsoup4 ; extra == 'templates'
Requires-Dist: jinja2 ; extra == 'templates'
Requires-Dist: mako ; extra == 'templates'
Requires-Dist: django ; extra == 'templates'
Requires-Dist: chameleon ; extra == 'templates'
Requires-Dist: markdown ; extra == 'templates'
